LICENSE
MANIFEST.in
README.md
pyproject.toml
requirements.txt
setup.py
sippy/CCEvents.py
sippy/CLIManager.py
sippy/ESipHeaderCSV.py
sippy/ESipHeaderIgnore.py
sippy/External_command.py
sippy/FakeAccounting.py
sippy/MsgBody.py
sippy/MultipartMixBody.py
sippy/MyConfigParser.py
sippy/Network_server.py
sippy/RadiusAccounting.py
sippy/RadiusAuthorisation.py
sippy/Radius_client.py
sippy/SdpBody.py
sippy/SdpConnecton.py
sippy/SdpGeneric.py
sippy/SdpMedia.py
sippy/SdpMediaDescription.py
sippy/SdpOrigin.py
sippy/Signal.py
sippy/SipAddress.py
sippy/SipAddressHF.py
sippy/SipAllow.py
sippy/SipAlso.py
sippy/SipAuthorization.py
sippy/SipCCDiversion.py
sippy/SipCSeq.py
sippy/SipCallId.py
sippy/SipCiscoGUID.py
sippy/SipConf.py
sippy/SipContact.py
sippy/SipContentLength.py
sippy/SipContentType.py
sippy/SipDiversion.py
sippy/SipExpires.py
sippy/SipFrom.py
sippy/SipGenericHF.py
sippy/SipHeader.py
sippy/SipLogger.py
sippy/SipMaxForwards.py
sippy/SipMsg.py
sippy/SipNumericHF.py
sippy/SipPAssertedIdentity.py
sippy/SipPath.py
sippy/SipProxyAuthenticate.py
sippy/SipProxyAuthorization.py
sippy/SipRAck.py
sippy/SipRSeq.py
sippy/SipReason.py
sippy/SipRecordRoute.py
sippy/SipReferTo.py
sippy/SipReferredBy.py
sippy/SipRegistrationAgent.py
sippy/SipReplaces.py
sippy/SipRequest.py
sippy/SipResponse.py
sippy/SipRoute.py
sippy/SipServer.py
sippy/SipSupported.py
sippy/SipTo.py
sippy/SipTransactionManager.py
sippy/SipURL.py
sippy/SipUserAgent.py
sippy/SipVia.py
sippy/SipWWWAuthenticate.py
sippy/SipWarning.py
sippy/StatefulProxy.py
sippy/UA.py
sippy/UaStateConnected.py
sippy/UaStateDead.py
sippy/UaStateDisconnected.py
sippy/UaStateFailed.py
sippy/UaStateGeneric.py
sippy/UacStateCancelling.py
sippy/UacStateIdle.py
sippy/UacStateRinging.py
sippy/UacStateTrying.py
sippy/UacStateUpdating.py
sippy/UasStateIdle.py
sippy/UasStateRinging.py
sippy/UasStateTrying.py
sippy/UasStateUpdating.py
sippy/Udp_server.py
sippy/Wss_server.py
sippy/XMPP_server.py
sippy/__init__.py
sippy/b2bua.py
sippy/b2bua_simple.py
sippy.egg-info/PKG-INFO
sippy.egg-info/SOURCES.txt
sippy.egg-info/dependency_links.txt
sippy.egg-info/entry_points.txt
sippy.egg-info/requires.txt
sippy.egg-info/top_level.txt
