Metadata-Version: 2.4
Name: sippy
Version: 2.2.3
Summary: RFC3261 SIP Stack and Back-to-Back User Agent (B2BUA)
Home-page: http://www.b2bua.org/
Author: Sippy Software, Inc.
Author-email: sobomax@sippysoft.com
License: BSD
Keywords: sip,b2bua,voip,rfc3261,sippy
Classifier: License :: OSI Approved :: BSD License
Classifier: Operating System :: POSIX
Classifier: Programming Language :: Python
License-File: LICENSE
Requires-Dist: ElPeriodic>=1.1
Requires-Dist: pycryptodome
Requires-Dist: websockets
Dynamic: author
Dynamic: author-email
Dynamic: classifier
Dynamic: description
Dynamic: description-content-type
Dynamic: home-page
Dynamic: keywords
Dynamic: license
Dynamic: license-file
Dynamic: requires-dist
Dynamic: summary
